MANIFEST.in
setup.py
athletic_pandas/__init__.py
athletic_pandas/base.py
athletic_pandas/exceptions.py
athletic_pandas/helpers.py
athletic_pandas/mixins.py
athletic_pandas/models.py
athletic_pandas/tools.py
athletic_pandas.egg-info/PKG-INFO
athletic_pandas.egg-info/SOURCES.txt
athletic_pandas.egg-info/dependency_links.txt
athletic_pandas.egg-info/top_level.txt
athletic_pandas/algorithms/__init__.py
athletic_pandas/algorithms/critical_power.py
athletic_pandas/algorithms/heartrate_models.py
athletic_pandas/algorithms/main.py
athletic_pandas/algorithms/w_prime_balance.py
tests/__init__.py
tests/conftest.py
tests/test_models.py