Metadata-Version: 1.1
Name: athletic-pandas
Version: 0.8.0
Summary: Workout analysis
Home-page: https://github.com/AartGoossens/athletic_pandas
Author: Aart Goossens
Author-email: aart@goossens.me
License: UNKNOWN
Platform: UNKNOWN
Classifier: Programming Language :: Python
Classifier: Programming Language :: Python :: 3.6
Classifier: License :: OSI Approved :: MIT License
Classifier: Operating System :: OS Independent
Classifier: Development Status :: 3 - Alpha
Classifier: Intended Audience :: Developers
Classifier: Intended Audience :: Science/Research
Classifier: Topic :: Scientific/Engineering
